paratest_python/__init__.py
paratest_python/nose.py
paratest_python_nose-0.0.1.dist-info/DESCRIPTION.rst
paratest_python_nose-0.0.1.dist-info/METADATA
paratest_python_nose-0.0.1.dist-info/RECORD
paratest_python_nose-0.0.1.dist-info/WHEEL
paratest_python_nose-0.0.1.dist-info/entry_points.txt
paratest_python_nose-0.0.1.dist-info/metadata.json
paratest_python_nose-0.0.1.dist-info/top_level.txt
